cnpjalfanum/__init__.py
cnpjalfanum/validator.py
robotframework_cnpjalfanum-0.1.0.dist-info/licenses/LICENCE
robotframework_cnpjalfanum-0.1.0.dist-info/METADATA
robotframework_cnpjalfanum-0.1.0.dist-info/WHEEL
robotframework_cnpjalfanum-0.1.0.dist-info/top_level.txt
robotframework_cnpjalfanum-0.1.0.dist-info/RECORD
