Metadata-Version: 2.4
Name: robotframework-cnpjalfanum
Version: 0.1.0
Summary: Biblioteca Robot Framework para gerar e validar CNPJs alfanuméricos
Author-email: QA Iniciante <ro_jordao@hotmail.com>
License-Expression: Apache-2.0
Project-URL: Homepage, https://github.com/Srjordao/robotframework-cnpjalfanum
Project-URL: Documentation, https://github.com/Srjordao/robotframework-cnpjalfanum
Keywords: robotframework,cnpj,alfanumérico,validação,qa
Classifier: Programming Language :: Python :: 3
Classifier: Framework :: Robot Framework
Classifier: Operating System :: OS Independent
Requires-Python: >=3.8
License-File: LICENCE
Requires-Dist: robotframework>=6.0
Dynamic: license-file
